sdl2dll/__init__.py
sdl2dll/initcheck.py
sdl2dll/dll/libSDL2-2.0.so
sdl2dll/dll/libSDL2_gfx-1.0.so
sdl2dll/dll/libSDL2_image-2.0.so
sdl2dll/dll/libSDL2_mixer-2.0.so
sdl2dll/dll/libSDL2_ttf-2.0.so
sdl2dll/dll/libavif.so.16
sdl2dll/dll/libdav1d.so.6
sdl2dll/dll/libgme.so.0
sdl2dll/dll/libogg.so.0
sdl2dll/dll/libopus.so.0
sdl2dll/dll/libopusfile.so.0
sdl2dll/dll/libtiff.so.5
sdl2dll/dll/libwavpack.so.1
sdl2dll/dll/libwebp.so.1.0.3
sdl2dll/dll/libwebpdemux.so.2.6.0
sdl2dll/dll/libxmp.so.4
pysdl2_dll-2.32.0.dist-info/LICENSE
pysdl2_dll-2.32.0.dist-info/LICENSE.SDL2.txt
pysdl2_dll-2.32.0.dist-info/LICENSE.avif.txt
pysdl2_dll-2.32.0.dist-info/LICENSE.dav1d.txt
pysdl2_dll-2.32.0.dist-info/LICENSE.gme.txt
pysdl2_dll-2.32.0.dist-info/LICENSE.ogg-vorbis.txt
pysdl2_dll-2.32.0.dist-info/LICENSE.opus.txt
pysdl2_dll-2.32.0.dist-info/LICENSE.opusfile.txt
pysdl2_dll-2.32.0.dist-info/LICENSE.tiff.txt
pysdl2_dll-2.32.0.dist-info/LICENSE.wavpack.txt
pysdl2_dll-2.32.0.dist-info/LICENSE.webp.txt
pysdl2_dll-2.32.0.dist-info/LICENSE.xmp.txt
pysdl2_dll-2.32.0.dist-info/METADATA
pysdl2_dll-2.32.0.dist-info/WHEEL
pysdl2_dll-2.32.0.dist-info/top_level.txt
pysdl2_dll-2.32.0.dist-info/RECORD
