Metadata-Version: 2.1
Name: pysdl2-dll
Version: 2.32.0
Summary: Pre-built SDL2 binaries for PySDL2
Home-page: https://github.com/a-hurst/pysdl2-dll
Author: Austin Hurst
Author-email: mynameisaustinhurst@gmail.com
License: Mozilla Public License Version 2.0
Classifier: Development Status :: 4 - Beta
Classifier: License :: OSI Approved :: Mozilla Public License 2.0 (MPL 2.0)
Classifier: Operating System :: MacOS
Classifier: Operating System :: Microsoft :: Windows
Classifier: Operating System :: POSIX :: Linux
Classifier: Programming Language :: Python
Classifier: Programming Language :: Python :: 2.7
Classifier: Programming Language :: Python :: 3
Classifier: Topic :: Software Development :: Libraries
License-File: LICENSE
